gaurav/__init__.py
gaurav/__main__.py
gaurav/cli.py
gaurav-0.1.0.dist-info/METADATA
gaurav-0.1.0.dist-info/WHEEL
gaurav-0.1.0.dist-info/entry_points.txt
gaurav-0.1.0.dist-info/top_level.txt
gaurav-0.1.0.dist-info/RECORD
